MANIFEST.in
README.md
setup.cfg
setup.py
rbiparser/__init__.py
rbiparser/banks.json
rbiparser/console.py
rbiparser/filters.json
rbiparser.egg-info/PKG-INFO
rbiparser.egg-info/SOURCES.txt
rbiparser.egg-info/dependency_links.txt
rbiparser.egg-info/entry_points.txt
rbiparser.egg-info/requires.txt
rbiparser.egg-info/top_level.txt