Metadata-Version: 1.1
Name: rbiparser
Version: 0.6.0
Summary: A utility for downloading, parsing and sanitizing bank database (IFSC, MICR, address etc.) Excel sheets from the RBI website.
Home-page: https://github.com/knadh/rbiparser
Author: Kailash Nadh
Author-email: kailash@nadh.in
License: MIT License
Download-URL: https://github.com/knadh/rbiparser
Platform: UNKNOWN
Classifier: Development Status :: 4 - Beta
Classifier: Intended Audience :: Developers
Classifier: Programming Language :: Python
Classifier: License :: OSI Approved :: MIT License
Classifier: Programming Language :: Python :: 2.6
Classifier: Programming Language :: Python :: 2.7
Classifier: Topic :: Software Development :: Libraries :: Python Modules
Classifier: Topic :: Database
Classifier: Topic :: Software Development :: Libraries
